{
 "meta": {
  "checked_at": "2026-07-11T19:20Z",
  "overall": "healthy",
  "stale_count": 0,
  "dead_count": 0,
  "heartbeat_dead_count": 0,
  "total": 10
 },
 "files": [
  {
   "file": "strikes.json",
   "agent": "npz-data (strikes)",
   "generated_at": null,
   "age_hours": null,
   "data_age_hours": null,
   "threshold_hours": 18,
   "heartbeat_at": "2026-07-11T19:01Z",
   "heartbeat_age_hours": 0.3,
   "heartbeat_threshold_hours": 72,
   "heartbeat_stale": false,
   "status": "unknown"
  },
  {
   "file": "fuel-state.json",
   "agent": "npz-data (npz)",
   "generated_at": "2026-07-11T18:20:00Z",
   "age_hours": 1.0,
   "data_age_hours": 1.0,
   "threshold_hours": 24,
   "heartbeat_at": "2026-07-11T18:06Z",
   "heartbeat_age_hours": 1.2,
   "heartbeat_threshold_hours": 72,
   "heartbeat_stale": false,
   "status": "ok"
  },
  {
   "file": "history-crimea.json",
   "agent": "npz-data (history)",
   "generated_at": "2026-07-11",
   "age_hours": 19.3,
   "data_age_hours": 19.3,
   "threshold_hours": 36,
   "heartbeat_at": "2026-07-11T18:28Z",
   "heartbeat_age_hours": 0.9,
   "heartbeat_threshold_hours": 72,
   "heartbeat_stale": false,
   "status": "ok"
  },
  {
   "file": "roads.json",
   "agent": "npz-data (roads)",
   "generated_at": "2026-07-11T23:50Z",
   "age_hours": 0.0,
   "data_age_hours": 0.0,
   "threshold_hours": 36,
   "heartbeat_at": "2026-07-11T18:48Z",
   "heartbeat_age_hours": 0.5,
   "heartbeat_threshold_hours": 72,
   "heartbeat_stale": false,
   "status": "ok"
  },
  {
   "file": "fuel-availability.json",
   "agent": "fuel-availability",
   "generated_at": "2026-07-11T08:41:51Z",
   "age_hours": 10.6,
   "data_age_hours": 10.6,
   "threshold_hours": 18,
   "heartbeat_at": "2026-07-11T12:23Z",
   "heartbeat_age_hours": 7.0,
   "heartbeat_threshold_hours": 72,
   "heartbeat_stale": false,
   "status": "ok"
  },
  {
   "file": "fuel-voices.json",
   "agent": "fuel-voices",
   "generated_at": "2026-07-11T16:50Z",
   "age_hours": 2.5,
   "data_age_hours": 2.5,
   "threshold_hours": 24,
   "heartbeat_at": "2026-07-11T16:44Z",
   "heartbeat_age_hours": 2.6,
   "heartbeat_threshold_hours": 72,
   "heartbeat_stale": false,
   "status": "ok"
  },
  {
   "file": "grid-state.json",
   "agent": "grid-status",
   "generated_at": "2026-07-11T21:00Z",
   "age_hours": 0.0,
   "data_age_hours": 0.0,
   "threshold_hours": 18,
   "heartbeat_at": "2026-07-11T18:54Z",
   "heartbeat_age_hours": 0.4,
   "heartbeat_threshold_hours": 72,
   "heartbeat_stale": false,
   "status": "ok"
  },
  {
   "file": "radar-state.json",
   "agent": "radar-state",
   "generated_at": "2026-07-11T19:20:03.797548Z",
   "age_hours": 0.0,
   "data_age_hours": 0.0,
   "threshold_hours": 0.5,
   "heartbeat_at": "2026-07-11T19:10Z",
   "heartbeat_age_hours": 0.2,
   "heartbeat_threshold_hours": 2,
   "heartbeat_stale": false,
   "status": "ok"
  },
  {
   "file": "forecast.json",
   "agent": "forecast-economy",
   "generated_at": "2026-07-06",
   "age_hours": 139.3,
   "data_age_hours": 139.3,
   "threshold_hours": 200,
   "heartbeat_at": "2026-07-06T07:16Z",
   "heartbeat_age_hours": 132.1,
   "heartbeat_threshold_hours": 200,
   "heartbeat_stale": false,
   "status": "ok"
  },
  {
   "file": "economy.json",
   "agent": "forecast-economy",
   "generated_at": "2026-07-07",
   "age_hours": 115.3,
   "data_age_hours": 115.3,
   "threshold_hours": 200,
   "heartbeat_at": "2026-07-06T07:18Z",
   "heartbeat_age_hours": 132.0,
   "heartbeat_threshold_hours": 200,
   "heartbeat_stale": false,
   "status": "ok"
  }
 ]
}