{
  "type": "state",
  "version": 23,
  "geo_parser_version": 4,
  "regions": {
    "Калужская область": {
      "name": "Калужская область",
      "bpla": false,
      "bplaDim": false,
      "uab": false,
      "uabDim": false,
      "fpv": false,
      "rocket": false,
      "rocket_level": false,
      "aviation": false,
      "pvo": false,
      "explosionOnRegion": false,
      "bplaLaunchAnim": false,
      "rocketOnRegion": false,
      "fill": "#d8c06a",
      "last_event_ts": 1784044663,
      "source_text": "14.07.2026 18:57 МСК\nКалужская область Тульская область Московская область внимание по бпла"
    },
    "Смоленская область": {
      "name": "Смоленская область",
      "bpla": false,
      "bplaDim": false,
      "uab": false,
      "uabDim": false,
      "fpv": false,
      "rocket": false,
      "rocket_level": false,
      "aviation": false,
      "pvo": false,
      "explosionOnRegion": false,
      "bplaLaunchAnim": false,
      "rocketOnRegion": false,
      "fill": "#d8c06a",
      "last_event_ts": 1784038452,
      "source_text": "14.07.2026 17:14 МСК\nСмоленская область Московская область внимание по бпла"
    },
    "Херсонская область": {
      "name": "Херсонская область",
      "bpla": false,
      "bplaDim": false,
      "uab": false,
      "uabDim": false,
      "fpv": false,
      "rocket": false,
      "rocket_level": false,
      "aviation": false,
      "pvo": false,
      "explosionOnRegion": false,
      "bplaLaunchAnim": false,
      "rocketOnRegion": false,
      "fill": "#d8c06a",
      "last_event_ts": 1784036683,
      "source_text": "14.07.2026 16:44 МСК\nКаланчак в направлении Армянск Опасность по БПЛА Хорнет"
    },
    "Курская область": {
      "name": "Курская область",
      "bpla": false,
      "bplaDim": false,
      "uab": false,
      "uabDim": false,
      "fpv": false,
      "rocket": true,
      "rocket_level": true,
      "aviation": false,
      "pvo": false,
      "explosionOnRegion": false,
      "bplaLaunchAnim": false,
      "rocketOnRegion": false,
      "fill": "#dc2626",
      "last_event_ts": 1784037481,
      "source_text": "14.07.2026 16:58 МСК\nБелгород, Белгородский район и ситуативно Белгородская область! Ракетная опасность! Займите Безопасные места! Потенциальная опасность для Курской области и Воронежской области внимание по бпла\n\n14.07.2026 13:36 МСК\nРыльск внимание по БПЛА Крыло со стороны Фонова - Звягин от Щекино Рыльского района"
    },
    "Адыгея": {
      "name": "Адыгея",
      "bpla": false,
      "bplaDim": false,
      "uab": false,
      "uabDim": false,
      "fpv": false,
      "rocket": false,
      "rocket_level": false,
      "aviation": false,
      "pvo": false,
      "explosionOnRegion": false,
      "bplaLaunchAnim": false,
      "rocketOnRegion": false,
      "fill": "#d8c06a",
      "last_event_ts": 1784049078,
      "source_text": "14.07.2026 20:11 МСК\nРеспублика Адыгея внимание по бпла"
    },
    "Костромская область": {
      "name": "Костромская область",
      "bpla": false,
      "bplaDim": false,
      "uab": false,
      "uabDim": false,
      "fpv": false,
      "rocket": false,
      "rocket_level": false,
      "aviation": false,
      "pvo": false,
      "explosionOnRegion": false,
      "bplaLaunchAnim": false,
      "rocketOnRegion": false,
      "fill": "#d8c06a",
      "last_event_ts": 1784016311,
      "source_text": "14.07.2026 11:05 МСК\nКостромская область внимание по бпла"
    },
    "Краснодарский край": {
      "name": "Краснодарский край",
      "bpla": false,
      "bplaDim": false,
      "uab": false,
      "uabDim": false,
      "fpv": false,
      "rocket": false,
      "rocket_level": false,
      "aviation": false,
      "pvo": false,
      "explosionOnRegion": false,
      "bplaLaunchAnim": false,
      "rocketOnRegion": false,
      "fill": "#d8c06a",
      "last_event_ts": 1784049042,
      "source_text": "14.07.2026 20:10 МСК\nМайкоп и далее на восток Тревога по БПЛА Краснодарский край"
    },
    "Севастополь": {
      "name": "Севастополь",
      "bpla": false,
      "bplaDim": false,
      "uab": false,
      "uabDim": false,
      "fpv": false,
      "rocket": false,
      "rocket_level": false,
      "aviation": false,
      "pvo": false,
      "explosionOnRegion": false,
      "bplaLaunchAnim": false,
      "rocketOnRegion": false,
      "fill": "#d8c06a",
      "last_event_ts": 1784049306,
      "source_text": "14.07.2026 20:15 МСК\nГород-герой Севастополь ❤️ ❤️ ❤️ внимание по бпла"
    },
    "Донецкая Народная Республика": {
      "name": "Донецкая Народная Республика",
      "bpla": false,
      "bplaDim": false,
      "uab": false,
      "uabDim": false,
      "fpv": false,
      "rocket": true,
      "rocket_level": true,
      "aviation": false,
      "pvo": false,
      "explosionOnRegion": false,
      "bplaLaunchAnim": false,
      "rocketOnRegion": false,
      "fill": "#dc2626",
      "last_event_ts": 1784049313,
      "source_text": "14.07.2026 17:25 МСК\nКурахово ДНР ракетная опасность\n\n14.07.2026 20:15 МСК\nНовоазовск, ДНР опасность по БПЛА на электротяге и БПЛА Хорнет"
    },
    "Владимирская область": {
      "name": "Владимирская область",
      "bpla": false,
      "bplaDim": false,
      "uab": false,
      "uabDim": false,
      "fpv": false,
      "rocket": false,
      "rocket_level": false,
      "aviation": false,
      "pvo": false,
      "explosionOnRegion": false,
      "bplaLaunchAnim": false,
      "rocketOnRegion": false,
      "fill": "#d8c06a",
      "last_event_ts": 1784047022,
      "source_text": "14.07.2026 19:37 МСК\nМеленковский район Владимирская область Фиксация БПЛА"
    },
    "Москва": {
      "name": "Москва",
      "bpla": false,
      "bplaDim": false,
      "uab": false,
      "uabDim": false,
      "fpv": false,
      "rocket": false,
      "rocket_level": false,
      "aviation": false,
      "pvo": false,
      "explosionOnRegion": false,
      "bplaLaunchAnim": false,
      "rocketOnRegion": false,
      "fill": "#d8c06a",
      "last_event_ts": 1784047396,
      "source_text": "14.07.2026 19:43 МСК\nГО Домодедово Московская область Работа ПВО по БПЛА Меры безопасности"
    },
    "Белгородская область": {
      "name": "Белгородская область",
      "bpla": false,
      "bplaDim": false,
      "uab": false,
      "uabDim": false,
      "fpv": false,
      "rocket": true,
      "rocket_level": true,
      "aviation": false,
      "pvo": false,
      "explosionOnRegion": false,
      "bplaLaunchAnim": false,
      "rocketOnRegion": false,
      "fill": "#dc2626",
      "last_event_ts": 1784046434,
      "source_text": "14.07.2026 16:58 МСК\nБелгород, Белгородский район и ситуативно Белгородская область! Ракетная опасность! Займите Безопасные места! Потенциальная опасность для Курской области и Воронежской области внимание по бпла\n\n14.07.2026 19:27 МСК\nДальний Валуйского района Опасность по БПЛА Хорнет"
    },
    "Воронежская область": {
      "name": "Воронежская область",
      "bpla": false,
      "bplaDim": false,
      "uab": false,
      "uabDim": false,
      "fpv": false,
      "rocket": true,
      "rocket_level": true,
      "aviation": false,
      "pvo": false,
      "explosionOnRegion": false,
      "bplaLaunchAnim": false,
      "rocketOnRegion": false,
      "fill": "#dc2626",
      "last_event_ts": 1784037481,
      "source_text": "14.07.2026 16:58 МСК\nБелгород, Белгородский район и ситуативно Белгородская область! Ракетная опасность! Займите Безопасные места! Потенциальная опасность для Курской области и Воронежской области внимание по бпла"
    },
    "Орловская область": {
      "name": "Орловская область",
      "bpla": false,
      "bplaDim": false,
      "uab": false,
      "uabDim": false,
      "fpv": false,
      "rocket": false,
      "rocket_level": false,
      "aviation": false,
      "pvo": false,
      "explosionOnRegion": false,
      "bplaLaunchAnim": false,
      "rocketOnRegion": false,
      "fill": "#d8c06a",
      "last_event_ts": 1784044635,
      "source_text": "14.07.2026 18:57 МСК\nБрянская область Орловская область Тревога по БПЛА Сохраняется Меры безопасности при БПЛА"
    },
    "Автономная Республика Крым": {
      "name": "Автономная Республика Крым",
      "bpla": false,
      "bplaDim": false,
      "uab": false,
      "uabDim": false,
      "fpv": false,
      "rocket": false,
      "rocket_level": false,
      "aviation": false,
      "pvo": false,
      "explosionOnRegion": false,
      "bplaLaunchAnim": false,
      "rocketOnRegion": false,
      "fill": "#d8c06a",
      "last_event_ts": 1784049306,
      "source_text": "14.07.2026 20:15 МСК\nГород-герой Севастополь ❤️ ❤️ ❤️ внимание по бпла"
    },
    "Ярославская область": {
      "name": "Ярославская область",
      "bpla": false,
      "bplaDim": false,
      "uab": false,
      "uabDim": false,
      "fpv": false,
      "rocket": false,
      "rocket_level": false,
      "aviation": false,
      "pvo": false,
      "explosionOnRegion": false,
      "bplaLaunchAnim": false,
      "rocketOnRegion": false,
      "fill": "#d8c06a",
      "last_event_ts": 1784016318,
      "source_text": "14.07.2026 11:05 МСК\nЯрославская область Опасность по БПЛА"
    },
    "Тверская область": {
      "name": "Тверская область",
      "bpla": false,
      "bplaDim": false,
      "uab": false,
      "uabDim": false,
      "fpv": false,
      "rocket": false,
      "rocket_level": false,
      "aviation": false,
      "pvo": false,
      "explosionOnRegion": false,
      "bplaLaunchAnim": false,
      "rocketOnRegion": false,
      "fill": "#d8c06a",
      "last_event_ts": 1784031412,
      "source_text": "14.07.2026 15:16 МСК\nЗубцовский район Тверская область Фиксация БПЛА"
    },
    "Запорожская область": {
      "name": "Запорожская область",
      "bpla": false,
      "bplaDim": false,
      "uab": false,
      "uabDim": false,
      "fpv": false,
      "rocket": true,
      "rocket_level": true,
      "aviation": false,
      "pvo": false,
      "explosionOnRegion": false,
      "bplaLaunchAnim": false,
      "rocketOnRegion": false,
      "fill": "#dc2626",
      "last_event_ts": 1784041077,
      "source_text": "14.07.2026 14:23 МСК\nФилия, Богатырь, Угледар, Комар, Великая Новосёлка и близлежащие ДНР Степногорск, Васильевка, Гуляйполе, Пологи Запорожская область РФ Авиационная ракетная бомбовая опасность\n\n14.07.2026 17:57 МСК\nРайновка - Приморск Опасность по БПЛА Запорожская область РФ"
    },
    "Московская область": {
      "name": "Московская область",
      "bpla": false,
      "bplaDim": false,
      "uab": false,
      "uabDim": false,
      "fpv": false,
      "rocket": false,
      "rocket_level": false,
      "aviation": false,
      "pvo": false,
      "explosionOnRegion": false,
      "bplaLaunchAnim": false,
      "rocketOnRegion": false,
      "fill": "#d8c06a",
      "last_event_ts": 1784046420,
      "source_text": "14.07.2026 19:27 МСК\nДомодедово Московская область внимание по бпла"
    },
    "Тамбовская область": {
      "name": "Тамбовская область",
      "bpla": false,
      "bplaDim": false,
      "uab": false,
      "uabDim": false,
      "fpv": false,
      "rocket": false,
      "rocket_level": false,
      "aviation": false,
      "pvo": false,
      "explosionOnRegion": false,
      "bplaLaunchAnim": false,
      "rocketOnRegion": false,
      "fill": "#d8c06a",
      "last_event_ts": 1784012004,
      "source_text": "14.07.2026 09:53 МСК\nТамбовская область внимание по бпла"
    },
    "Луганская Народная Республика": {
      "name": "Луганская Народная Республика",
      "bpla": false,
      "bplaDim": false,
      "uab": false,
      "uabDim": false,
      "fpv": false,
      "rocket": false,
      "rocket_level": false,
      "aviation": false,
      "pvo": false,
      "explosionOnRegion": false,
      "bplaLaunchAnim": false,
      "rocketOnRegion": false,
      "fill": "#d8c06a",
      "last_event_ts": 1784043253,
      "source_text": "14.07.2026 18:34 МСК\nСтаробельск и близлежащие Опасность по БПЛА Сохраняется ЛНР"
    },
    "Брянская область": {
      "name": "Брянская область",
      "bpla": false,
      "bplaDim": false,
      "uab": false,
      "uabDim": false,
      "fpv": false,
      "rocket": false,
      "rocket_level": false,
      "aviation": false,
      "pvo": false,
      "explosionOnRegion": false,
      "bplaLaunchAnim": false,
      "rocketOnRegion": false,
      "fill": "#d8c06a",
      "last_event_ts": 1784044635,
      "source_text": "14.07.2026 18:57 МСК\nБрянская область Орловская область Тревога по БПЛА Сохраняется Меры безопасности при БПЛА"
    },
    "Тульская область": {
      "name": "Тульская область",
      "bpla": false,
      "bplaDim": false,
      "uab": false,
      "uabDim": false,
      "fpv": false,
      "rocket": false,
      "rocket_level": false,
      "aviation": false,
      "pvo": false,
      "explosionOnRegion": false,
      "bplaLaunchAnim": false,
      "rocketOnRegion": false,
      "fill": "#d8c06a",
      "last_event_ts": 1784045415,
      "source_text": "14.07.2026 19:10 МСК\nАлексин Тульская область внимание по бпла"
    }
  },
  "timestamp": 1784049667.254115,
  "fetched_at": "2026-07-14T17:21:07Z"
}